[
  {
    "_id": "7bwkk2imqrr3lf4",
    "createdAt": "2026-06-24T07:27:34.960Z",
    "updatedAt": "2026-06-24T07:27:34.960Z",
    "title": "Global Tech Summit 2026",
    "description": "Join top industry leaders, researchers, and developers to explore AI innovation, next-gen cloud architectures, and the roadmap of web engineering. Features workshops, panels, and networking lounges.",
    "date": "2026-10-15T09:00:00.000Z",
    "time": "09:00 AM - 05:00 PM",
    "venue": "Silicon Valley Convention Center, CA",
    "category": "Tech",
    "price": 199,
    "capacity": 250,
    "ticketsSold": 0,
    "imageUrl": "https://images.unsplash.com/photo-1540575467063-178a50c2df87?auto=format&fit=crop&w=800&q=80",
    "organizer": "x7n5771mqrr3lau"
  },
  {
    "_id": "2ioyytpmqrr3lf4",
    "createdAt": "2026-06-24T07:27:34.960Z",
    "updatedAt": "2026-06-24T07:27:34.960Z",
    "title": "Neon Summer Music Festival",
    "description": "Dance under the stars at the biggest electronic music beach party of the year. Featuring an international lineup of DJs, mesmerizing laser light shows, and premium food trucks.",
    "date": "2026-08-22T16:00:00.000Z",
    "time": "04:00 PM - 02:00 AM",
    "venue": "Sunset Sands Beachfront, FL",
    "category": "Music",
    "price": 55,
    "capacity": 500,
    "ticketsSold": 0,
    "imageUrl": "https://images.unsplash.com/photo-1470225620780-dba8ba36b745?auto=format&fit=crop&w=800&q=80",
    "organizer": "x7n5771mqrr3lau"
  },
  {
    "_id": "i6340x6mqrr3lf4",
    "createdAt": "2026-06-24T07:27:34.960Z",
    "updatedAt": "2026-06-24T07:27:34.960Z",
    "title": "International Culinary Gala",
    "description": "Treat your taste buds to an exclusive evening of fine dining. Watch live demonstrations from Michelin-starred chefs, participate in wine pairing workshops, and sample gourmet cuisines from 12 countries.",
    "date": "2026-09-05T18:00:00.000Z",
    "time": "06:00 PM - 10:00 PM",
    "venue": "The Grand Ballroom, NY",
    "category": "Food",
    "price": 85,
    "capacity": 120,
    "ticketsSold": 0,
    "imageUrl": "https://images.unsplash.com/photo-1556910103-1c02745aae4d?auto=format&fit=crop&w=800&q=80",
    "organizer": "x7n5771mqrr3lau"
  },
  {
    "_id": "re25eypmqrr3lf4",
    "createdAt": "2026-06-24T07:27:34.960Z",
    "updatedAt": "2026-06-24T07:27:34.960Z",
    "title": "Championship Charity Fun Run",
    "description": "Lace up your running shoes and join our 5K charity run! 100% of registration donations go towards supporting local children's hospitals. Free snacks, t-shirts, and participation medals included!",
    "date": "2026-07-12T07:30:00.000Z",
    "time": "07:30 AM - 11:00 AM",
    "venue": "Central Park Green Loop, NY",
    "category": "Sports",
    "price": 0,
    "capacity": 400,
    "ticketsSold": 0,
    "imageUrl": "https://images.unsplash.com/photo-1476480862126-209bfaa8edc8?auto=format&fit=crop&w=800&q=80",
    "organizer": "x7n5771mqrr3lau"
  },
  {
    "_id": "4jvs8a9mqrr3lf4",
    "createdAt": "2026-06-24T07:27:34.960Z",
    "updatedAt": "2026-06-24T07:27:34.960Z",
    "title": "Modern Digital Art Exhibition",
    "description": "Explore the boundaries of art and technology. This showcase highlights leading virtual reality sculptors, generative artificial intelligence canvas works, and interactive neon projection installations.",
    "date": "2026-11-02T10:00:00.000Z",
    "time": "10:00 AM - 08:00 PM",
    "venue": "Metropolis Contemporary Art Gallery",
    "category": "Arts",
    "price": 15,
    "capacity": 100,
    "ticketsSold": 0,
    "imageUrl": "https://images.unsplash.com/photo-1460661419201-fd4cecdf8a8b?auto=format&fit=crop&w=800&q=80",
    "organizer": "x7n5771mqrr3lau"
  }
]